{"Date":"31.01.2021","Time":"12:00","CurrentDayIndex":1,"Resultation":6.5}
{"Date":"11.02.2021","Time":"13:00","CurrentDayIndex":1,"Resultation":7.5}
{"Date":"11.02.2021","Time":"13:00","CurrentDayIndex":1,"Resultation":7.5}
{"Date":"11.02.2021","Time":"13:00","CurrentDayIndex":1,"Resultation":7.5}
{"Date":"11.02.2021","Time":"20:11","CurrentDayIndex":1,"Resultation":15.5}
{"Date":"11.02.2021","Time":"20:15","CurrentDayIndex":1,"Resultation":3.3}
{"Date":"12.02.2021","Time":"10:17","CurrentDayIndex":1,"Resultation":6.3}
{"Date":"12.02.2021","Time":"14:15","CurrentDayIndex":1,"Resultation":11.0}
{"Date":"13.02.2021","Time":"08:16","CurrentDayIndex":1,"Resultation":7.0}
{"Date":"14.02.2021","Time":"17:14","CurrentDayIndex":1,"Resultation":5.8}
{"Date":"14.02.2021","Time":"20:16","CurrentDayIndex":1,"Resultation":9.3}
{"Date":"08.03.2021","Time":"13:03","CurrentDayIndex":1,"Resultation":7.7}
{"Date":"08.03.2021","Time":"13:06","CurrentDayIndex":1,"Resultation":2.7}
{"Date":"09.03.2021","Time":"11:47","CurrentDayIndex":1,"Resultation":6.5}
{"Date":"09.03.2021","Time":"12:24","CurrentDayIndex":1,"Resultation":4.5}
{"Date":"09.03.2021","Time":"12:25","CurrentDayIndex":1,"Resultation":7.4}
{"Date":"09.03.2021","Time":"12:36","CurrentDayIndex":1,"Resultation":9.8}
{"Date":"09.03.2021","Time":"12:43","CurrentDayIndex":1,"Resultation":10}
{"Date":"09.03.2021","Time":"12:45","CurrentDayIndex":1,"Resultation":13.5}
{"Date":"09.03.2021","Time":"12:50","CurrentDayIndex":1,"Resultation":9.3}
{"Date":"09.03.2021","Time":"13:02","CurrentDayIndex":1,"Resultation":15.6}
{"Date":"09.03.2021","Time":"13:52","CurrentDayIndex":1,"Resultation":11.1}
{"Date":"11.03.2021","Time":"15:36","CurrentDayIndex":1,"Resultation":17.3}
{"Date":"11.03.2021","Time":"17:26","CurrentDayIndex":1,"Resultation":4.3}
{"Date":"11.03.2021","Time":"17:35","CurrentDayIndex":1,"Resultation":4.4}
{"Date":"11.03.2021","Time":"17:40","CurrentDayIndex":1,"Resultation":4.6}
{"Date":"16.03.2021","Time":"18:05","CurrentDayIndex":1,"Resultation":13.37}
{"Date":"16.03.2021","Time":"18:05","CurrentDayIndex":1,"Resultation":8.2}
{"Date":"17.03.2021","Time":"22:45","CurrentDayIndex":1,"Resultation":7.3}
{"Date":"17.03.2021","Time":"22:50","CurrentDayIndex":1,"Resultation":13.2}
{"Date":"17.03.2021","Time":"22:54","CurrentDayIndex":1,"Resultation":4.2}
{"Date":"18.03.2021","Time":"17:48","CurrentDayIndex":1,"Resultation":8.3}
{"Date":"18.03.2021","Time":"18:04","CurrentDayIndex":1,"Resultation":3.4}
{"Date":"25.03.2021","Time":"15:31","CurrentDayIndex":1,"Resultation":7.3}
{"Date":"28.03.2021","Time":"20:30","CurrentDayIndex":1,"Resultation":10.3}
